{
	"credit": "Made with Blockbench",
	"textures": {
		"0": "ikisugimusicplayer:block/soundfileuploader",
		"particle": "ikisugimusicplayer:block/soundfileuploader"
	},
	"elements": [
		{
			"from": [6, 0.5, 3],
			"to": [10, 12.5, 13],
			"rotation": {"angle": 0, "axis": "y", "origin": [14, 8, 8]},
			"faces": {
				"north": {"uv": [2.75, 0, 4, 3.25], "texture": "#0"},
				"east": {"uv": [0, 3.25, 2.75, 6.5], "texture": "#0"},
				"south": {"uv": [2.75, 3.25, 4, 6.5], "texture": "#0"},
				"west": {"uv": [0, 0, 2.75, 3.25], "texture": "#0"},
				"up": {"uv": [5, 0, 6, 2.75], "texture": "#0"},
				"down": {"uv": [4, 0, 5, 2.75], "texture": "#0"}
			}
		},
		{
			"from": [6, 0, 3],
			"to": [7, 0.5, 4],
			"rotation": {"angle": 0, "axis": "y", "origin": [14, 8, 8]},
			"faces": {
				"north": {"uv": [0, 6.5, 0.25, 6.75], "texture": "#0"},
				"east": {"uv": [0, 6.5, 0.25, 6.75], "texture": "#0"},
				"south": {"uv": [0, 6.5, 0.25, 6.75], "texture": "#0"},
				"west": {"uv": [0, 6.5, 0.25, 6.75], "texture": "#0"},
				"up": {"uv": [0, 6.5, 0.25, 6.75], "texture": "#0"},
				"down": {"uv": [0, 6.5, 0.25, 6.75], "texture": "#0"}
			}
		},
		{
			"from": [9, 0, 3],
			"to": [10, 0.5, 4],
			"rotation": {"angle": 0, "axis": "y", "origin": [14, 8, 8]},
			"faces": {
				"north": {"uv": [0, 6.5, 0.25, 6.75], "texture": "#0"},
				"east": {"uv": [0, 6.5, 0.25, 6.75], "texture": "#0"},
				"south": {"uv": [0, 6.5, 0.25, 6.75], "texture": "#0"},
				"west": {"uv": [0, 6.5, 0.25, 6.75], "texture": "#0"},
				"up": {"uv": [0, 6.5, 0.25, 6.75], "texture": "#0"},
				"down": {"uv": [0, 6.5, 0.25, 6.75], "texture": "#0"}
			}
		},
		{
			"from": [9, 0, 12],
			"to": [10, 0.5, 13],
			"rotation": {"angle": 0, "axis": "y", "origin": [14, 8, 8]},
			"faces": {
				"north": {"uv": [0, 6.5, 0.25, 6.75], "texture": "#0"},
				"east": {"uv": [0, 6.5, 0.25, 6.75], "texture": "#0"},
				"south": {"uv": [0, 6.5, 0.25, 6.75], "texture": "#0"},
				"west": {"uv": [0, 6.5, 0.25, 6.75], "texture": "#0"},
				"up": {"uv": [0, 6.5, 0.25, 6.75], "texture": "#0"},
				"down": {"uv": [0, 6.5, 0.25, 6.75], "texture": "#0"}
			}
		},
		{
			"from": [6, 0, 12],
			"to": [7, 0.5, 13],
			"rotation": {"angle": 0, "axis": "y", "origin": [14, 8, 8]},
			"faces": {
				"north": {"uv": [0, 6.5, 0.25, 6.75], "texture": "#0"},
				"east": {"uv": [0, 6.5, 0.25, 6.75], "texture": "#0"},
				"south": {"uv": [0, 6.5, 0.25, 6.75], "texture": "#0"},
				"west": {"uv": [0, 6.5, 0.25, 6.75], "texture": "#0"},
				"up": {"uv": [0, 6.5, 0.25, 6.75], "texture": "#0"},
				"down": {"uv": [0, 6.5, 0.25, 6.75], "texture": "#0"}
			}
		}
	],
	"display": {
		"thirdperson_righthand": {
			"rotation": [75, 45, 0],
			"translation": [0, 2.5, 0],
			"scale": [0.375, 0.375, 0.375]
		},
		"firstperson_righthand": {
			"rotation": [0, 45, 0],
			"translation": [0, 4.2, 0],
			"scale": [0.6, 0.6, 0.6]
		},
		"firstperson_lefthand": {
			"rotation": [0, 225, 0],
			"translation": [0, 4.2, 0],
			"scale": [0.6, 0.6, 0.6]
		},
		"ground": {
			"translation": [0, 3, 0],
			"scale": [0.25, 0.25, 0.25]
		},
		"gui": {
			"rotation": [30, 225, 0],
			"scale": [0.625, 0.625, 0.625]
		},
		"fixed": {
			"scale": [0.5, 0.5, 0.5]
		}
	}
}